[
  {
    "branch": "R",
    "class": "org.hdiv.filter.ValidatorHelperRequest",
    "tool": "RefactoringMiner",
    "refactoringInfo": "Extract Variable\terror : ValidatorError in method protected restoreState(request HttpServletRequest, target String) : ValidatorHelperResult from class org.hdiv.filter.ValidatorHelperRequest",
    "description": {
      "filePath": "hdiv-core/src/main/java/org/hdiv/filter/ValidatorHelperRequest.java",
      "startLine": 623,
      "endLine": 624,
      "startColumn": 21,
      "endColumn": 36,
      "codeElementType": "VARIABLE_DECLARATION_STATEMENT",
      "description": "extracted variable declaration",
      "codeElement": "error : ValidatorError"
    },
    "line": "628"
  },
  {
    "branch": "R",
    "class": "org.hdiv.filter.ValidatorHelperRequest",
    "tool": "RefactoringMiner",
    "refactoringInfo": "Extract Variable\terror : ValidatorError in method protected restoreState(request HttpServletRequest, target String) : ValidatorHelperResult from class org.hdiv.filter.ValidatorHelperRequest",
    "description": {
      "filePath": "hdiv-core/src/main/java/org/hdiv/filter/ValidatorHelperRequest.java",
      "startLine": 639,
      "endLine": 639,
      "startColumn": 19,
      "endColumn": 98,
      "codeElementType": "VARIABLE_DECLARATION_STATEMENT",
      "description": "extracted variable declaration",
      "codeElement": "error : ValidatorError"
    },
    "line": "644"
  }
]
