[
  {
    "type": "CONFLICT",
    "label": "SVFA conflict",
    "interference": [
      {
        "branch": "",
        "class": "de.devland.esperandro.generation.CollectionActionGenerator",
        "line": "57"
      },
      {
        "branch": "",
        "class": "de.devland.esperandro.generation.CollectionActionGenerator",
        "line": "57"
      },
      {
        "branch": "",
        "class": "de.devland.esperandro.generation.CollectionActionGenerator",
        "line": "63"
      }
    ]
  }
]