[
  [
    {
      "class": "org.hdiv.components.support.OutputLinkComponentProcessor",
      "refactoringInfo": [
        "Extract And Move Method\tpublic getHdivStateParameterName(request HttpServletRequest) : String extracted from public processOutputLink(context FacesContext, component HtmlOutputLink) : void in class org.hdiv.components.support.OutputLinkComponentProcessor & moved to class org.hdiv.util.HDIVUtil"
      ],
      "line": "71",
      "filePath": "hdiv-jsf/src/main/java/org/hdiv/components/support/OutputLinkComponentProcessor.java",
      "branch": "R"
    },
    {
      "class": "org.hdiv.components.support.OutputLinkComponentProcessor",
      "refactoringInfo": [
        "Extract Variable\thdivParameter : String in method public processOutputLink(context FacesContext, component HtmlOutputLink) : void from class org.hdiv.components.support.OutputLinkComponentProcessor"
      ],
      "line": "97",
      "filePath": "hdiv-jsf/src/main/java/org/hdiv/components/support/OutputLinkComponentProcessor.java",
      "branch": "L"
    }
  ]
]
