[
  [
    {
      "class": "org.tomitribe.crest.maven.CrestCommandLoaderDescriptorGeneratorMojo",
      "line": "62",
      "refactoringInfo": [
        "Replace Generic With Diamond\tTreeSet<String> with TreeSet<> in method public execute() : void from class org.tomitribe.crest.maven.CrestCommandLoaderDescriptorGeneratorMojo"
      ]
    },
    {
      "class": "org.tomitribe.crest.maven.CrestCommandLoaderDescriptorGeneratorMojo",
      "line": "73",
      "refactoringInfo": [
        "Try With Resources\ttry(FileWriter writer=new FileWriter(output)) in method public execute() : void from class org.tomitribe.crest.maven.CrestCommandLoaderDescriptorGeneratorMojo"
      ]
    }
  ]
]
