[
  [
    {
      "branch": "",
      "class": "org.unigram.docvalidator.Main",
      "line": "85"
    },
    {
      "branch": "",
      "class": "org.unigram.docvalidator.Main",
      "line": "100"
    },
    {
      "branch": "",
      "class": "org.unigram.docvalidator.Main",
      "line": "107"
    }
  ],
  [
    {
      "branch": "",
      "class": "org.unigram.docvalidator.Main",
      "line": "85"
    },
    {
      "branch": "",
      "class": "org.unigram.docvalidator.Main",
      "line": "100"
    },
    {
      "branch": "",
      "class": "org.unigram.docvalidator.Main",
      "line": "107"
    }
  ],
  [
    {
      "branch": "",
      "class": "org.unigram.docvalidator.Main",
      "line": "85"
    },
    {
      "branch": "",
      "class": "org.unigram.docvalidator.Main",
      "line": "100"
    },
    {
      "branch": "",
      "class": "org.unigram.docvalidator.Main",
      "line": "107"
    }
  ]
]