[
  {
    "type": "OAINTER",
    "label": "OA conflict",
    "interference": [
      {
        "branch": "L",
        "class": "org.asteriskjava.live.internal.AbstractLiveObject",
        "line": "61"
      },
      {
        "branch": "R",
        "class": "org.asteriskjava.live.internal.AbstractLiveObject",
        "line": "61"
      }
    ]
  },
  {
    "type": "OAINTER",
    "label": "OA conflict",
    "interference": [
      {
        "branch": "L",
        "class": "org.asteriskjava.live.internal.AbstractLiveObject",
        "line": "66"
      },
      {
        "branch": "R",
        "class": "org.asteriskjava.live.internal.AbstractLiveObject",
        "line": "66"
      }
    ]
  },
  {
    "type": "CONFLICT",
    "label": "SVFA conflict",
    "interference": [
      {
        "branch": "",
        "class": "org.asteriskjava.live.internal.AbstractLiveObject",
        "line": "61"
      },
      {
        "branch": "",
        "class": "org.asteriskjava.live.internal.AbstractLiveObject",
        "line": "70"
      }
    ]
  },
  {
    "type": "CONFLICT",
    "label": "SVFA conflict",
    "interference": [
      {
        "branch": "",
        "class": "org.asteriskjava.live.internal.AbstractLiveObject",
        "line": "66"
      },
      {
        "branch": "",
        "class": "org.asteriskjava.live.internal.AbstractLiveObject",
        "line": "70"
      }
    ]
  }
]