[
  {
    "type": "CONFLICT",
    "label": "SVFA conflict",
    "interference": [
      {
        "branch": "",
        "class": "org.ez18n.apt.processor.CSVReportProcessor",
        "line": "98"
      },
      {
        "branch": "",
        "class": "org.ez18n.apt.processor.CSVReportProcessor",
        "line": "98"
      },
      {
        "branch": "",
        "class": "org.ez18n.apt.processor.CSVReportProcessor",
        "line": "116"
      },
      {
        "branch": "",
        "class": "org.ez18n.apt.processor.CSVReportProcessor",
        "line": "116"
      },
      {
        "branch": "",
        "class": "org.ez18n.apt.processor.CSVReportProcessor",
        "line": "116"
      },
      {
        "branch": "",
        "class": "org.ez18n.apt.processor.CSVReportProcessor",
        "line": "116"
      },
      {
        "branch": "",
        "class": "org.ez18n.apt.processor.CSVReportProcessor",
        "line": "116"
      }
    ]
  }
]